{
  "plan_info": {
    "name": "AARP Medicare Advantage from UHC DC-0002 (PPO)",
    "organization": "UnitedHealthcare",
    "type": "Medicare Advantage with drug coverage",
    "id": "H2406-082-0"
  },
  "premiums": {
    "Total monthly premium": "$46.00",
    "Health premium": "$0.00",
    "Drug premium": "$46.00",
    "Standard Part B premium": "$202.90",
    "Part B premium reduction": "Not offered"
  },
  "deductibles": {
    "Health deductible": "$0.00",
    "Drug deductible": "$600.00"
  },
  "maximum_out_of_pocket": {
    "Maximum you pay for health servicesOnce you spend this amount for covered services in a year, your plan pays 100% for your care.": "$10,100 In and Out-of-network\n$6,700 In-network"
  },
  "contact_info": {
    "Plan address": "P.O. Box 30770\nSalt Lake City, UT 84130"
  },
  "benefits": {
    "Doctor services": {
      "Primary doctor visit": "In-network: $0 copay\nOut-of-network: $20 copay",
      "Specialist visit": "In-network: $0-$45 copay\nOut-of-network: $70 copay"
    },
    "Tests, labs, & imaging": {
      "Diagnostic tests & proceduresTests done to confirm or uncover the presence of an illness or disease.": "In-network: $20 copay\nOut-of-network: 40% coinsurance",
      "Lab services": "In-network: $0 copay\nOut-of-network: $0 copay",
      "Diagnostic radiology services (like MRI)": "In-network: $0-$260 copay\nOut-of-network: 40% coinsurance",
      "Outpatient x-rays": "In-network: $30 copay\nOut-of-network: $50 copay",
      "Emergency care": "$130 copay",
      "Urgent care": "$0-$50 copay"
    },
    "Hospital services": {
      "Inpatient hospital coverage": "In-network:\nTier 1\n$425 per day for days 1-6\n$0 per day for days 7-90\n$0 per stay\nOut-of-network:\n40% per stay",
      "Outpatient hospital coverage": "In-network: $0-$425 copay\nOut-of-network: 40% coinsurance"
    },
    "Skilled nursing facility": {
      "Skilled nursing facility": "In-network:\nTier 1\n$0 per day for days 1-20\n$218 per day for days 21-100\nOut-of-network:\n$250 per day for days 1-100\n$0 per stay"
    },
    "Preventive services": {
      "Preventive services": "In-network: $0 copay\nOut-of-network: 0%-40% coinsurance"
    },
    "Ambulance": {
      "Ground ambulance": "In-network: $275 copay\nOut-of-network: $275 copay"
    },
    "Therapy services": {
      "Occupational therapy visit": "In-network: $40 copay\nOut-of-network: $70 copay",
      "Physical therapy & speech & language therapy visit": "In-network: $40 copay\nOut-of-network: $70 copay"
    },
    "Mental health services": {
      "Outpatient group therapy with a psychiatrist": "In-network: $15 copay\nOut-of-network: $30 copay",
      "Outpatient individual therapy with a psychiatrist": "In-network: $0-$25 copay\nOut-of-network: $40 copay",
      "Outpatient group therapy visit": "In-network: $15 copay\nOut-of-network: $30 copay",
      "Outpatient individual therapy visit": "In-network: $0-$25 copay\nOut-of-network: $40 copay"
    },
    "Opioid treatment program services": {
      "Opioid treatment program services": "In-network: $0 copay\nOut-of-network: $0 copay"
    },
    "Other services": {
      "Durable medical equipment (like wheelchairs & oxygen)": "In-network: 20% coinsurance\nOut-of-network: 50% coinsurance",
      "Prosthetics (like braces, artificial limbs)": "In-network: 20% coinsurance\nOut-of-network: 50% coinsurance",
      "Dialysis": "In-network: 20% coinsurance\nOut-of-network: 20% coinsurance",
      "Diabetes supplies": "In-network: $0 copay\nOut-of-network: 50% coinsurance"
    },
    "Pharmacies": {},
    "Costs by drug tier - Standard retail pharmacy drug cost for 1 month": {
      "Preferred Generic": "$0.00 copay",
      "Generic": "$10.00 copay",
      "Preferred Brand": "15% coinsurance",
      "Non-Preferred Drug": "36% coinsurance",
      "Specialty Tier": "26% coinsurance"
    },
    "Part B drugs": {
      "Part B insulin": "In-network: 0%-20% coinsurance\nOut-of-network: 40% coinsurance",
      "Chemotherapy drugs": "In-network: 0%-20% coinsurance\nOut-of-network: 40% coinsurance",
      "Other Part B drugs": "In-network: 0%-20% coinsurance\nOut-of-network: 0%-40% coinsurance"
    },
    "Hearing": {
      "Hearing exam": "In-network: $0 copay\nOut-of-network: $70 copay",
      "Fitting/evaluation": "Not covered",
      "Hearing aids - prescription": "In-network: $199-$1249 copay\nOut-of-network: $199-$1249 copay",
      "Hearing aids - over the counter": "In-network: $199-$829 copay\nOut-of-network: $199-$829 copay"
    },
    "Preventive dental": {
      "Oral exam": "In-network: $0 copay\nOut-of-network: $0 copay",
      "Cleaning": "In-network: $0 copay\nOut-of-network: $0 copay",
      "Fluoride treatment": "In-network: $0 copay\nOut-of-network: $0 copay",
      "Dental x-rays": "In-network: $0 copay\nOut-of-network: $0 copay"
    },
    "Comprehensive dental": {
      "Restorative services": "In-network: 50% coinsurance\nOut-of-network: 50% coinsurance",
      "Endodontics": "In-network: 50% coinsurance\nOut-of-network: 50% coinsurance",
      "Periodontics": "In-network: 50% coinsurance\nOut-of-network: 50% coinsurance",
      "Prosthodontics, removable": "In-network: 50% coinsurance\nOut-of-network: 50% coinsurance",
      "Prosthodontics, fixed": "In-network: 50% coinsurance\nOut-of-network: 50% coinsurance",
      "Maxillofacial prosthetics": "In-network: 50% coinsurance\nOut-of-network: 50% coinsurance",
      "Implant services": "Not covered",
      "Oral and maxillofacial surgery": "In-network: 50% coinsurance\nOut-of-network: 50% coinsurance",
      "Orthodontics": "Not covered",
      "Adjunctive general services": "In-network: 50% coinsurance\nOut-of-network: 50% coinsurance"
    },
    "Vision": {
      "Routine eye exam": "In-network: $0 copay\nOut-of-network: $70 copay",
      "Contact lenses": "In-network: $0 copay\nOut-of-network: $0 copay",
      "Eyeglasses (frames & lenses)": "Not covered",
      "Eyeglass frames only": "In-network: $0 copay\nOut-of-network: $0 copay",
      "Eyeglass lenses only": "In-network: $0-$153 copay\nOut-of-network: $0-$153 copay",
      "Upgrades": "Not covered"
    },
    "Medically-approved non-opioid pain management services": {
      "Chiropractic services": "Not covered",
      "Acupuncture": "Not covered",
      "Massage therapy": "Not covered",
      "Alternative therapies": "Not covered"
    },
    "More benefits": {
      "Health Education": "Not covered",
      "Counseling Services": "Not covered",
      "Support for Caregivers of Enrollees": "Not covered",
      "Personal Emergency Response System (PERS)": "Not covered",
      "Fitness benefit": "In-network: $0 copay\nOut-of-network: $0 copay",
      "Transportation services for non-emergency care: Any health-related locations": "Not covered",
      "Transportation services for non-emergency care: Plan-approved locations": "Not covered",
      "Over the counter drug benefits": "In-network: $0 copay\nOut-of-network: $0 copay",
      "In-home support services": "Not covered",
      "Home and bathroom safety devices": "In-network: $0 copay\nOut-of-network: $0 copay",
      "Meals for short duration": "In-network: $0 copay\nOut-of-network: $0 copay",
      "Annual physical exams": "In-network: $0 copay",
      "Telehealth": "In-network: $0 copay",
      "Worldwide emergency": "$0 copay",
      "Post discharge in-home medication reconciliation": "Not covered",
      "Re-admission prevention": "Not covered",
      "Wigs for hair loss related to chemotherapy": "Not covered",
      "Weight management programs": "Not covered",
      "Adult day health services": "Not covered",
      "Home-based palliative care": "Not covered"
    }
  },
  "drug_coverage": {},
  "extra_benefits": {}
}